{
    "title": "",
    "released_year": "",
    "album": "",
    "genre": "හමු වුණේ නැත",
    "lyrics": "",
    "lyricist": "",
    "musician": "නිමේෂ් කුලසිංහ",
    "singer": "",
    "mp3_listen": {
        "songhub": "https://songhub.lk/song/susumaka-welila-hamuwemu-aye-sansare-ruwan-hettiarachchi-shashika-nisansala",
        "spotify": "https://open.spotify.com/track/2RKhJ1hdQ3hagkVthHC2mZ?autoplay=true",
        "apple": "https://music.apple.com/lk/album/susumaka-welila/1539103458?i=1539103459"
    },
    "video_watch": "https://www.youtube.com/watch?v=q4ZadvT7y2E",
    "download": "https://songhub.lk/song/674de400-bd0a-11e9-baaa-13b0a0bb9461/download?token=iTkadM41D8xpU74KmLUs23B9yKhqSXloITvBx6Dt",
    "metaphor": [
        {
            "lyrics_part": "",
            "meaning": "",
            "type": "",
            "source_domain": "",
            "target_domain": ""
        }
    ]
}